{"stat.useItem.minecraft.bow":4,"stat.useItem.minecraft.iron_axe":38,"stat.leaveGame":3,"stat.mineBlock.minecraft.cobblestone":19,"stat.useItem.minecraft.bookshelf":12,"stat.mineBlock.minecraft.brown_mushroom":2,"stat.useItem.minecraft.diamond_sword":119,"stat.mineBlock.minecraft.stained_glass_pane":13,"stat.mineBlock.minecraft.stained_glass":2,"stat.swimOneCm":6057,"stat.useItem.minecraft.snow":4,"stat.climbOneCm":21621,"stat.useItem.minecraft.planks":78,"achievement.buildWorkBench":6,"stat.enderchestOpened":2,"stat.useItem.minecraft.dirt":37,"achievement.exploreAllBiomes":{"value":0,"progress":["Cold Taiga","Cold Taiga Hills","Plains","FrozenRiver","Ice Plains","Jungle","Forest","River","JungleHills","Taiga","Extreme Hills","Swampland","Hell","Ice Mountains"]},"stat.mineBlock.minecraft.stone_brick_stairs":6,"stat.craftItem.minecraft.furnace":1,"stat.useItem.minecraft.egg":142,"stat.craftItem.minecraft.stone_axe":1,"achievement.diamonds":3,"stat.craftItem.minecraft.stone_pickaxe":2,"stat.killEntity.Enderman":3,"stat.craftItem.minecraft.cobblestone_wall":192,"stat.mineBlock.minecraft.carpet":1,"stat.craftItem.minecraft.stone_sword":1,"stat.flyOneCm":436670,"stat.useItem.minecraft.ender_pearl":1,"achievement.buildPickaxe":6,"stat.mineBlock.minecraft.sand":11,"stat.useItem.minecraft.cooked_beef":1,"achievement.buildBetterPickaxe":4,"stat.mineBlock.minecraft.iron_ore":18,"stat.timeSinceDeath":4507,"stat.useItem.minecraft.iron_pickaxe":8,"stat.useItem.minecraft.sign":1,"stat.useItem.minecraft.spawn_egg":1,"stat.craftItem.minecraft.wooden_pickaxe":1,"stat.breakItem.minecraft.flint_and_steel":1,"stat.useItem.minecraft.hardened_clay":2,"stat.mineBlock.minecraft.vine":13,"stat.mineBlock.minecraft.hopper":72,"stat.furnaceInteraction":15,"stat.useItem.minecraft.cooked_porkchop":7,"stat.mineBlock.minecraft.coal_ore":46,"stat.killEntity.Creeper":3,"achievement.buildSword":4,"achievement.mineWood":149,"stat.useItem.minecraft.dropper":1,"stat.mineBlock.minecraft.stained_hardened_clay":27,"stat.useItem.minecraft.trapdoor":2,"stat.sprintOneCm":350008,"stat.useItem.minecraft.diamond_shovel":34,"stat.useItem.minecraft.fence":4,"stat.craftItem.minecraft.stick":8,"achievement.openInventory":223,"stat.mineBlock.minecraft.diamond_ore":1,"stat.useItem.minecraft.flint_and_steel":65,"stat.mineBlock.minecraft.fence":8,"stat.mineBlock.minecraft.crafting_table":3,"stat.useItem.minecraft.pumpkin_pie":1,"stat.useItem.minecraft.diamond_pickaxe":409,"stat.mineBlock.minecraft.quartz_block":32,"stat.useItem.minecraft.hopper":72,"stat.entityKilledBy.Creeper":1,"achievement.killEnemy":45,"stat.useItem.minecraft.beef":2,"achievement.buildFurnace":2,"stat.deaths":8,"stat.mineBlock.minecraft.planks":142,"stat.drop":37,"stat.playOneMinute":234863,"stat.useItem.minecraft.wooden_sword":3,"stat.killEntity.Sheep":3,"stat.killEntity.Zombie":27,"stat.mineBlock.minecraft.tallgrass":18,"stat.craftItem.minecraft.cooked_mutton":1,"stat.diveOneCm":832,"stat.chestOpened":481,"stat.craftItem.minecraft.cooked_porkchop":9,"stat.mineBlock.minecraft.anvil":1,"stat.useItem.minecraft.diamond_axe":188,"stat.useItem.minecraft.apple":4,"stat.useItem.minecraft.carpet":1,"stat.jump":2628,"stat.useItem.minecraft.sand":13,"stat.fallOneCm":1183,"stat.useItem.minecraft.stone_axe":150,"stat.crouchOneCm":56819,"achievement.killCow":2,"stat.mineBlock.minecraft.chest":68,"stat.craftItem.minecraft.chest":11,"stat.craftItem.minecraft.iron_ingot":30,"stat.craftItem.minecraft.torch":24,"stat.mineBlock.minecraft.hardened_clay":2,"stat.craftItem.minecraft.hopper":2,"stat.useItem.minecraft.cooked_chicken":1,"stat.craftingTableInteraction":30,"stat.dropperInspected":1,"stat.useItem.minecraft.sapling":1,"achievement.blazeRod":1,"stat.damageTaken":4339,"stat.mineBlock.minecraft.furnace":1,"stat.mineBlock.minecraft.torch":7,"stat.useItem.minecraft.wooden_pickaxe":44,"stat.useItem.minecraft.furnace":2,"stat.craftItem.minecraft.wooden_sword":1,"stat.mineBlock.minecraft.fence_gate":1,"stat.entityKilledBy.Zombie":1,"stat.useItem.minecraft.stone_pickaxe":241,"stat.breakItem.minecraft.stone_axe":1,"stat.mineBlock.minecraft.glass":11,"stat.useItem.minecraft.stone_sword":88,"stat.damageDealt":23380,"stat.killEntity.Cow":1,"stat.mineBlock.minecraft.dirt":152,"stat.useItem.minecraft.crafting_table":5,"stat.killEntity.Pig":5,"stat.walkOneCm":1356786,"stat.useItem.minecraft.torch":9,"stat.useItem.minecraft.bread":27,"stat.useItem.minecraft.chest":50,"stat.playerKills":14,"stat.useItem.minecraft.pumpkin":2,"stat.useItem.minecraft.log":4,"stat.useItem.minecraft.cobblestone":2,"stat.craftItem.minecraft.crafting_table":3,"stat.mineBlock.minecraft.double_plant":10,"stat.breakItem.minecraft.stone_pickaxe":1,"stat.mineBlock.minecraft.wool":1,"stat.useItem.minecraft.stained_hardened_clay":245,"stat.killEntity.Skeleton":7,"achievement.portal":4,"stat.mineBlock.minecraft.stonebrick":25,"stat.craftItem.minecraft.planks":160,"stat.killEntity.Chicken":4,"stat.killEntity.Spider":8,"stat.useItem.minecraft.jungle_door":1,"stat.mobKills":64,"stat.useItem.minecraft.stonebrick":1,"stat.mineBlock.minecraft.log":119,"stat.craftItem.minecraft.shears":1,"achievement.acquireIron":7,"stat.useItem.minecraft.cobblestone_wall":11,"stat.mineBlock.minecraft.leaves":58,"stat.mineBlock.minecraft.redstone_ore":3,"stat.mineBlock.minecraft.stone":401,"stat.useItem.minecraft.fishing_rod":32,"stat.craftItem.minecraft.jungle_door":3}