{"stat.flyOneCm":9783,"stat.deaths":1,"stat.walkOneCm":25746,"stat.jump":33,"stat.swimOneCm":851,"stat.mineBlock.minecraft.sand":1,"stat.playOneMinute":4296,"achievement.openInventory":3,"stat.entityKilledBy.Zombie":1,"stat.leaveGame":1,"stat.damageTaken":428,"stat.damageDealt":325,"stat.mineBlock.minecraft.ice":2,"stat.crouchOneCm":956,"stat.timeSinceDeath":1028,"stat.dispenserInspected":1,"stat.sprintOneCm":12813,"stat.mobKills":1,"achievement.exploreAllBiomes":{"value":0,"progress":["Forest","Taiga","Extreme Hills","Extreme Hills Edge"]},"stat.mineBlock.minecraft.tallgrass":1,"stat.diveOneCm":1226}