{"stat.chestOpened":3,"stat.walkOneCm":91645,"achievement.openInventory":12,"stat.horseOneCm":369,"stat.leaveGame":3,"stat.furnaceInteraction":2,"stat.useItem.minecraft.carrot":1,"stat.useItem.minecraft.cooked_porkchop":1,"stat.flyOneCm":59233,"stat.jump":185,"stat.swimOneCm":723,"stat.playOneMinute":17599,"stat.climbOneCm":1010,"stat.useItem.minecraft.cooked_beef":1,"stat.timeSinceDeath":17599,"stat.sprintOneCm":54394,"achievement.exploreAllBiomes":{"value":0,"progress":["Beach","Forest","River","Ocean","Plains","Extreme Hills"]},"stat.diveOneCm":2035}