{"stat.flyOneCm":148027,"stat.walkOneCm":113946,"stat.jump":362,"stat.swimOneCm":198,"stat.mineBlock.minecraft.lapis_ore":1,"stat.playOneMinute":76434,"stat.pickup.minecraft.coal":2,"stat.fallOneCm":14647,"stat.climbOneCm":4151,"stat.useItem.minecraft.cooked_mutton":1,"stat.leaveGame":1,"stat.sneakTime":984,"stat.damageTaken":386,"stat.crouchOneCm":1739,"stat.timeSinceDeath":76434,"stat.sprintOneCm":97642,"stat.useItem.minecraft.iron_pickaxe":11,"stat.mineBlock.minecraft.coal_ore":2,"stat.mineBlock.minecraft.stone":8,"stat.diveOneCm":15838,"stat.pickup.minecraft.dye":1}